{
  "main": {
    "id": "52bccab515ec32eb",
    "type": "split",
    "children": [
      {
        "id": "8bf36213a11fd394",
        "type": "tabs",
        "children": [
          {
            "id": "58f4c7204c164af7",
            "type": "leaf",
            "state": {
              "type": "markdown",
              "state": {
                "file": "Computer Graphics Self-Study/Fundamentals of Computer Graphics.md",
                "mode": "source",
                "source": false
              },
              "icon": "lucide-file",
              "title": "Fundamentals of Computer Graphics"
            }
          }
        ]
      }
    ],
    "direction": "vertical"
  },
  "left": {
    "id": "31462b144bfdc6bc",
    "type": "split",
    "children": [
      {
        "id": "32a6aa9538711dd7",
        "type": "tabs",
        "children": [
          {
            "id": "e887abae232e2633",
            "type": "leaf",
            "state": {
              "type": "file-explorer",
              "state": {
                "sortOrder": "byModifiedTime"
              },
              "icon": "lucide-folder-closed",
              "title": "Files"
            }
          },
          {
            "id": "c7952e2ae45c44e9",
            "type": "leaf",
            "state": {
              "type": "search",
              "state": {
                "query": "",
                "matchingCase": false,
                "explainSearch": false,
                "collapseAll": false,
                "extraContext": false,
                "sortOrder": "alphabetical"
              },
              "icon": "lucide-search",
              "title": "Search"
            }
          },
          {
            "id": "116d8cae0bee16d6",
            "type": "leaf",
            "state": {
              "type": "starred",
              "state": {},
              "icon": "lucide-file",
              "title": "Plugin no longer active"
            }
          },
          {
            "id": "7063a69376deb659",
            "type": "leaf",
            "state": {
              "type": "outline",
              "state": {
                "file": "Computer Graphics Self-Study/Fundamentals of Computer Graphics.md"
              },
              "icon": "lucide-list",
              "title": "Outline of Fundamentals of Computer Graphics"
            }
          },
          {
            "id": "5bed3be80c518dcf",
            "type": "leaf",
            "state": {
              "type": "bookmarks",
              "state": {},
              "icon": "lucide-bookmark",
              "title": "Bookmarks"
            }
          }
        ]
      }
    ],
    "direction": "horizontal",
    "width": 278.99999809265137,
    "collapsed": true
  },
  "right": {
    "id": "78053effe92f6b21",
    "type": "split",
    "children": [
      {
        "id": "0a44f306315adc46",
        "type": "tabs",
        "children": [
          {
            "id": "2f3b833a9bc2bbd2",
            "type": "leaf",
            "state": {
              "type": "backlink",
              "state": {
                "file": "Computer Graphics Self-Study/Fundamentals of Computer Graphics.md",
                "collapseAll": false,
                "extraContext": false,
                "sortOrder": "alphabetical",
                "showSearch": false,
                "searchQuery": "",
                "backlinkCollapsed": false,
                "unlinkedCollapsed": false
              },
              "icon": "links-coming-in",
              "title": "Backlinks for Fundamentals of Computer Graphics"
            }
          },
          {
            "id": "eb398117cf66936d",
            "type": "leaf",
            "state": {
              "type": "outgoing-link",
              "state": {
                "file": "Computer Graphics Self-Study/Fundamentals of Computer Graphics.md",
                "linksCollapsed": false,
                "unlinkedCollapsed": true
              },
              "icon": "links-going-out",
              "title": "Outgoing links from Fundamentals of Computer Graphics"
            }
          },
          {
            "id": "8e505407aa012a08",
            "type": "leaf",
            "state": {
              "type": "advanced-tables-toolbar",
              "state": {},
              "icon": "lucide-file",
              "title": "Plugin no longer active"
            }
          },
          {
            "id": "865766689e5cbed9",
            "type": "leaf",
            "state": {
              "type": "wordle-view",
              "state": {},
              "icon": "lucide-file",
              "title": "Wordle"
            }
          },
          {
            "id": "e88c0db4b7cbf94c",
            "type": "leaf",
            "state": {
              "type": "git-view",
              "state": {},
              "icon": "git-pull-request",
              "title": "Source Control"
            }
          }
        ],
        "currentTab": 4
      }
    ],
    "direction": "horizontal",
    "width": 359.9287109375,
    "collapsed": true
  },
  "left-ribbon": {
    "hiddenItems": {
      "switcher:Open quick switcher": false,
      "graph:Open graph view": false,
      "canvas:Create new canvas": false,
      "templates:Insert template": false,
      "command-palette:Open command palette": false,
      "markdown-importer:Open format converter": false,
      "table-editor-obsidian:Advanced Tables Toolbar": false,
      "periodic-notes:Open today": false,
      "obsidian-git:Open Git source control": false,
      "notion-like-tables:Create loom": false
    }
  },
  "active": "58f4c7204c164af7",
  "lastOpenFiles": [
    "Computer Graphics Self-Study/Pasted image 20250110133327.png",
    "Computer Graphics Self-Study/Pasted image 20250110133251.png",
    "Fall 2021/Theory of Computation/Theory of Computation.md",
    "Computer Graphics Self-Study/Fundamentals of Computer Graphics.md",
    "Fall 2021/Theory of Computation/_Index_of_Theory of Computation.md",
    "Spring 2022/_Index_of_Spring 2022.md",
    "Spring 2022/Software Engineering/_Index_of_Software Engineering.md",
    "Fall 2021/Professional Practice/_Index_of_Professional Practice.md",
    "Fall 2021/Operating Systems/_Index_of_Operating Systems.md",
    "Fall 2021/Databases/Nihon-Go/_Index_of_Nihon-Go.md",
    "Spring 2022/Networks/_Index_of_Networks.md",
    "Fall 2021/Game Development/_Index_of_Game Development.md",
    "Fall 2021/_Index_of_Fall 2021.md",
    "Fall 2021/Databases/_Index_of_Databases.md",
    "Spring 2022/Data Analysis/_Index_of_Data Analysis.md",
    "Computer Graphics Self-Study/_Index_of_Computer Graphics Self-Study.md",
    "Spring 2022/Comptia Security+/_Index_of_Comptia Security+.md",
    "Spring 2022/Algorithms/_Index_of_Algorithms.md",
    "📗Textbooks/_Index_of_📗Textbooks.md",
    "_Daily_Notes/_Index_of__Daily_Notes.md",
    "_Index_of_Computer-Science.md",
    "Computer Graphics Self-Study/Computer Graphics Self-Study.md",
    "📗Textbooks/Fundamentals_of_Computer_Graphics_5th.epub",
    "📗Textbooks/A_First_Course_in_Database_Systems.pdf",
    "📗Textbooks/Intro_to_Theory_of_Computation_3rd.pdf",
    "📗Textbooks/Fundamentals of Computer Graphics, 5th Ed - Steve Marschner, Peter Shirley.epub",
    "📗Textbooks/Fundamentals of Computer Graphics.epub/ops/toc.ncx",
    "📗Textbooks/Fundamentals of Computer Graphics.epub/ops/content.opf",
    "📗Textbooks/Fundamentals of Computer Graphics.epub/ops/styles/9781000426359.css",
    "📗Textbooks/Fundamentals of Computer Graphics.epub/ops/styles",
    "📗Textbooks/Fundamentals of Computer Graphics.epub/ops/mathjax/jax/output/SVG/fonts/TeX/Typewriter/Regular/Other.js",
    "📗Textbooks/Fundamentals of Computer Graphics.epub/ops/mathjax/jax/output/SVG/fonts/TeX/Typewriter/Regular/Main.js",
    "📗Textbooks/Fundamentals of Computer Graphics.epub/ops/mathjax/images/MenuArrow-15.png",
    "📗Textbooks/Fundamentals of Computer Graphics.epub/ops/mathjax/images/CloseX-31.png",
    "📗Textbooks/Fundamentals of Computer Graphics.epub/ops/images/fig12_5.jpg",
    "📗Textbooks/Fundamentals of Computer Graphics.epub/ops/images/fig12_12.jpg",
    "📗Textbooks/Fundamentals of Computer Graphics.epub/ops/images/fig2_20.jpg",
    "📗Textbooks/Fundamentals of Computer Graphics.epub/ops/images/fig10_7.jpg",
    "📗Textbooks/Fundamentals of Computer Graphics.epub/ops/images/fig2_34.jpg",
    "📗Textbooks/Fundamentals of Computer Graphics.epub/ops/images/fig9_3.jpg",
    "📗Textbooks/Fundamentals of Computer Graphics.epub/ops/images/fig23_26.jpg",
    "📗Textbooks/Fundamentals of Computer Graphics.epub.md",
    "Fall 2021/Operating Systems/Operating Systems.md",
    "Science of Learning.md",
    "Spring 2022/Algorithms/Algo Final Exam Prep.md",
    "Spring 2022/Algorithms/Algorithms.md"
  ]
}